sdevelo/__init__.py
sdevelo/_config.py
sdevelo/_infer.py
sdevelo/_model.py
sdevelo/_pl.py
sdevelo/_sim.py
sdevelo-0.2.12.dist-info/.ipynb_checkpoints/PKG-INFO-checkpoint
sdevelo-0.2.12.dist-info/.ipynb_checkpoints/dependency_links-checkpoint.txt
sdevelo-0.2.12.dist-info/.ipynb_checkpoints/requires-checkpoint.txt
sdevelo-0.2.12.dist-info/LICENSE
sdevelo-0.2.12.dist-info/METADATA
sdevelo-0.2.12.dist-info/WHEEL
sdevelo-0.2.12.dist-info/top_level.txt
sdevelo-0.2.12.dist-info/RECORD
