Metadata-Version: 2.1
Name: sdevelo
Version: 0.2.12
Summary: SDEvelo: multivariate stochastic modeling for transcriptional dynamics with cell-specific latent time
Home-page: https://github.com/Liao-Xu/SDEvelo
Author: Xu Liao
Author-email: xu.smooth.liao@gmail.com
License: LICENSE
Classifier: Development Status :: 1 - Planning
Classifier: Programming Language :: Python :: 3
Classifier: License :: OSI Approved :: MIT License
Classifier: Operating System :: OS Independent
Requires-Python: >=3.8
License-File: LICENSE
Requires-Dist: anndata
Requires-Dist: matplotlib
Requires-Dist: numpy <2.0.0
Requires-Dist: scipy
Requires-Dist: scvelo
Requires-Dist: seaborn
Requires-Dist: torch
